gpib_ctypes/Gpib.py
gpib_ctypes/__init__.py
gpib_ctypes/gpib/__init__.py
gpib_ctypes/gpib/constants.py
gpib_ctypes/gpib/gpib.py
gpib_ctypes-0.3.0.dist-info/AUTHORS.rst
gpib_ctypes-0.3.0.dist-info/LICENSE
gpib_ctypes-0.3.0.dist-info/METADATA
gpib_ctypes-0.3.0.dist-info/WHEEL
gpib_ctypes-0.3.0.dist-info/top_level.txt
gpib_ctypes-0.3.0.dist-info/RECORD
