Metadata-Version: 1.1
Name: gpib-ctypes
Version: 0.3.0
Summary: GPIB interface for Python implemented using ctypes, API-compatible with linux-gpib.
Home-page: https://github.com/tivek/gpib_ctypes
Author: Tomislav Ivek
Author-email: tomislav.ivek@gmail.com
License: GNU General Public License v2
Keywords: gpib_ctypes
Platform: UNKNOWN
Classifier: Development Status :: 3 - Alpha
Classifier: Intended Audience :: Developers
Classifier: License :: OSI Approved :: GNU General Public License v2 (GPLv2)
Classifier: Natural Language :: English
Classifier: Programming Language :: Python :: 2
Classifier: Programming Language :: Python :: 2.6
Classifier: Programming Language :: Python :: 2.7
Classifier: Programming Language :: Python :: 3
Classifier: Programming Language :: Python :: 3.3
Classifier: Programming Language :: Python :: 3.4
Classifier: Programming Language :: Python :: 3.5
Classifier: Programming Language :: Python :: 3.6
Classifier: Programming Language :: Python :: 3.7
